README.md
setup.py
web_mother.egg-info/PKG-INFO
web_mother.egg-info/SOURCES.txt
web_mother.egg-info/dependency_links.txt
web_mother.egg-info/top_level.txt
webmother/__init__.py
webmother/employment.py
webmother/extra_passport.py
webmother/membership.py
webmother/passport.py
webmother/db/__init__.py
webmother/db/mongo.py
webmother/http_handler/__init__.py
webmother/http_handler/app_handler.py
webmother/http_handler/catalog_handler.py
webmother/http_handler/entrance_handler.py
webmother/http_handler/org_handler.py
webmother/http_handler/passport_handler.py
webmother/http_handler/person_handler.py
webmother/routes/__init__.py
webmother/routes/catalog.py
webmother/routes/entrance.py
webmother/routes/org.py
webmother/service/__init__.py
webmother/service/ctrl_app.py
webmother/service/ctrl_catalog.py
webmother/service/ctrl_entrance.py
webmother/service/ctrl_org.py
webmother/service/ctrl_passport.py
webmother/service/ctrl_person.py
webmother/service/async_wrap/__init__.py
webmother/service/async_wrap/ctrl_app.py
webmother/service/async_wrap/ctrl_catalog.py
webmother/service/async_wrap/ctrl_entrance.py
webmother/service/async_wrap/ctrl_org.py
webmother/service/async_wrap/ctrl_passport.py
webmother/service/async_wrap/ctrl_person.py
webmother/utils/__init__.py
webmother/utils/bson_util.py
webmother/utils/user_auth.py